nonebot_plugin_orm-0.8.3.dist-info/METADATA
nonebot_plugin_orm-0.8.3.dist-info/WHEEL
nonebot_plugin_orm-0.8.3.dist-info/entry_points.txt
nonebot_plugin_orm-0.8.3.dist-info/licenses/LICENSE
nonebot_plugin_orm/__init__.py
nonebot_plugin_orm/__main__.py
nonebot_plugin_orm/config.py
nonebot_plugin_orm/env.py
nonebot_plugin_orm/exception.py
nonebot_plugin_orm/migrate.py
nonebot_plugin_orm/model.py
nonebot_plugin_orm/param.py
nonebot_plugin_orm/py.typed
nonebot_plugin_orm/templates/generic/README
nonebot_plugin_orm/templates/generic/__init__.py
nonebot_plugin_orm/templates/generic/env.py
nonebot_plugin_orm/templates/generic/script.py.mako
nonebot_plugin_orm/templates/generic/versions/__init__.py
nonebot_plugin_orm/templates/multidb/README
nonebot_plugin_orm/templates/multidb/__init__.py
nonebot_plugin_orm/templates/multidb/env.py
nonebot_plugin_orm/templates/multidb/script.py.mako
nonebot_plugin_orm/templates/multidb/versions/__init__.py
nonebot_plugin_orm/utils.py
nonebot_plugin_orm-0.8.3.dist-info/RECORD
