Metadata-Version: 2.1
Name: nonebot-plugin-orm
Version: 0.8.3
Summary: SQLAlchemy ORM support for nonebot
Keywords: nonebot,orm,sqlalchemy
Author-Email: yanyongyu <yyy@nonebot.dev>, ProgramRipper <programripper@foxmail.com>
License: MIT
Project-URL: homepage, https://github.com/nonebot/plugin-orm
Project-URL: repository, https://github.com/nonebot/plugin-orm
Project-URL: documentation, https://github.com/nonebot/plugin-orm
Requires-Python: <4.0,>=3.9
Requires-Dist: alembic~=1.16
Requires-Dist: click~=8.1
Requires-Dist: importlib-metadata>=4.6; python_version < "3.10"
Requires-Dist: importlib-resources>=5.12; python_version < "3.12"
Requires-Dist: nonebot-plugin-localstore~=0.7
Requires-Dist: nonebot2~=2.4
Requires-Dist: sqlalchemy~=2.0
Requires-Dist: typing-extensions~=4.13
Provides-Extra: default
Requires-Dist: sqlalchemy[aiosqlite]; extra == "default"
Provides-Extra: mysql
Requires-Dist: sqlalchemy[aiomysql]; extra == "mysql"
Provides-Extra: asyncmy
Requires-Dist: sqlalchemy[asyncmy]; extra == "asyncmy"
Provides-Extra: aiomysql
Requires-Dist: sqlalchemy[aiomysql]; extra == "aiomysql"
Provides-Extra: postgresql
Requires-Dist: sqlalchemy[postgresql-psycopgbinary]; extra == "postgresql"
Provides-Extra: psycopg
Requires-Dist: sqlalchemy[postgresql-psycopgbinary]; extra == "psycopg"
Provides-Extra: asyncpg
Requires-Dist: sqlalchemy[postgresql-asyncpg]; extra == "asyncpg"
Provides-Extra: sqlite
Requires-Dist: sqlalchemy[aiosqlite]; extra == "sqlite"
Provides-Extra: aiosqlite
Requires-Dist: sqlalchemy[aiosqlite]; extra == "aiosqlite"
